betdaq/__init__.py
betdaq/apiclient.py
betdaq/baseclient.py
betdaq/compat.py
betdaq/enums.py
betdaq/exceptions.py
betdaq/filters.py
betdaq/utils.py
betdaq/classifiers/__init__.py
betdaq/classifiers/betting.py
betdaq/classifiers/marketdata.py
betdaq/endpoints/__init__.py
betdaq/endpoints/account.py
betdaq/endpoints/baseendpoint.py
betdaq/endpoints/betting.py
betdaq/endpoints/marketdata.py
betdaq/endpoints/trading.py
betdaq/errorparsers/__init__.py
betdaq/errorparsers/betting.py
betdaq/errorparsers/marketdata.py
betdaq/resources/__init__.py
betdaq/resources/accountresources.py
betdaq/resources/baseresources.py
betdaq/resources/bettingresources.py
betdaq/resources/marketdataresources.py
betdaq/resources/tradingresources.py
betdaq_retail-0.1.1.dist-info/METADATA
betdaq_retail-0.1.1.dist-info/WHEEL
betdaq_retail-0.1.1.dist-info/licenses/LICENSE
betdaq_retail-0.1.1.dist-info/RECORD
