Metadata-Version: 2.4
Name: betdaq-retail
Version: 0.1.1
Summary: BETDAQ Retail API Python wrapper
Project-URL: Homepage, https://github.com/betcode-org
Project-URL: Documentation, https://betcode-org.github.io/betdaq/
Project-URL: Repository, https://github.com/betcode-org/betdaq-retail.git
Project-URL: Bug Tracker, https://github.com/betcode-org/betdaq-retail/issues
Project-URL: Changelog, https://github.com/betcode-org/betdaq-retail/blob/master/HISTORY.rst
Author-email: Rory Cole <rory.cole1990@gmail.com>
License: MIT License
License-File: LICENSE
Classifier: License :: OSI Approved :: MIT License
Classifier: Operating System :: OS Independent
Classifier: Programming Language :: Python :: 3.8
Classifier: Programming Language :: Python :: 3.9
Classifier: Programming Language :: Python :: 3.10
Classifier: Programming Language :: Python :: 3.11
Classifier: Programming Language :: Python :: 3.12
Requires-Python: >=3.8
Requires-Dist: python-dateutil>=2.6.0
Requires-Dist: requests<2.33.0
Requires-Dist: zeep>=4.0.0
Provides-Extra: test
Requires-Dist: black==24.8.0; extra == 'test'
Requires-Dist: build; extra == 'test'
Requires-Dist: coverage; extra == 'test'
Requires-Dist: twine; extra == 'test'
